[{"Id": 1, "Name": null, "Description": null, "Attack": null, "Defense": null, "Special Attack": null, "Special Defense": null, "Speed": null, "Attack Speed ": null, "Crit Rate": null, "Crit Scale": null}, {"Id": 2, "Name": null, "Description": null, "Attack": null, "Defense": null, "Special Attack": null, "Special Defense": null, "Speed": null, "Attack Speed ": null, "Crit Rate": null, "Crit Scale": null}, {"Id": 3, "Name": null, "Description": null, "Attack": null, "Defense": null, "Special Attack": null, "Special Defense": null, "Speed": null, "Attack Speed ": null, "Crit Rate": null, "Crit Scale": null}, {"Id": 4, "Name": null, "Description": null, "Attack": null, "Defense": null, "Special Attack": null, "Special Defense": null, "Speed": null, "Attack Speed ": null, "Crit Rate": null, "Crit Scale": null}, {"Id": 5, "Name": null, "Description": null, "Attack": null, "Defense": null, "Special Attack": null, "Special Defense": null, "Speed": null, "Attack Speed ": null, "Crit Rate": null, "Crit Scale": null}, {"Id": 6, "Name": null, "Description": null, "Attack": null, "Defense": null, "Special Attack": null, "Special Defense": null, "Speed": null, "Attack Speed ": null, "Crit Rate": null, "Crit Scale": null}, {"Id": 7, "Name": null, "Description": null, "Attack": null, "Defense": null, "Special Attack": null, "Special Defense": null, "Speed": null, "Attack Speed ": null, "Crit Rate": null, "Crit Scale": null}, {"Id": 8, "Name": null, "Description": null, "Attack": null, "Defense": null, "Special Attack": null, "Special Defense": null, "Speed": null, "Attack Speed ": null, "Crit Rate": null, "Crit Scale": null}, {"Id": 9, "Name": null, "Description": null, "Attack": null, "Defense": null, "Special Attack": null, "Special Defense": null, "Speed": null, "Attack Speed ": null, "Crit Rate": null, "Crit Scale": null}, {"Id": 10, "Name": null, "Description": null, "Attack": null, "Defense": null, "Special Attack": null, "Special Defense": null, "Speed": null, "Attack Speed ": null, "Crit Rate": null, "Crit Scale": null}, {"Id": 11, "Name": null, "Description": null, "Attack": null, "Defense": null, "Special Attack": null, "Special Defense": null, "Speed": null, "Attack Speed ": null, "Crit Rate": null, "Crit Scale": null}, {"Id": 12, "Name": null, "Description": null, "Attack": null, "Defense": null, "Special Attack": null, "Special Defense": null, "Speed": null, "Attack Speed ": null, "Crit Rate": null, "Crit Scale": null}, {"Id": 13, "Name": null, "Description": null, "Attack": null, "Defense": null, "Special Attack": null, "Special Defense": null, "Speed": null, "Attack Speed ": null, "Crit Rate": null, "Crit Scale": null}, {"Id": 14, "Name": null, "Description": null, "Attack": null, "Defense": null, "Special Attack": null, "Special Defense": null, "Speed": null, "Attack Speed ": null, "Crit Rate": null, "Crit Scale": null}, {"Id": 15, "Name": null, "Description": null, "Attack": null, "Defense": null, "Special Attack": null, "Special Defense": null, "Speed": null, "Attack Speed ": null, "Crit Rate": null, "Crit Scale": null}, {"Id": 16, "Name": null, "Description": null, "Attack": null, "Defense": null, "Special Attack": null, "Special Defense": null, "Speed": null, "Attack Speed ": null, "Crit Rate": null, "Crit Scale": null}]